ltlf2dfa/__init__.py
ltlf2dfa/__version__.py
ltlf2dfa/base.py
ltlf2dfa/helpers.py
ltlf2dfa/ltlf.py
ltlf2dfa/ltlf2dfa.py
ltlf2dfa/pl.py
ltlf2dfa/pltlf.py
ltlf2dfa/symbols.py
ltlf2dfa/parser/__init__.py
ltlf2dfa/parser/ltlf.lark
ltlf2dfa/parser/ltlf.py
ltlf2dfa/parser/pl.lark
ltlf2dfa/parser/pl.py
ltlf2dfa/parser/pltlf.lark
ltlf2dfa/parser/pltlf.py
ltlf2dfa-1.0.2.data/data/ltlf2dfa/parser/ltlf.lark
ltlf2dfa-1.0.2.data/data/ltlf2dfa/parser/pl.lark
ltlf2dfa-1.0.2.data/data/ltlf2dfa/parser/pltlf.lark
ltlf2dfa-1.0.2.dist-info/LICENSE
ltlf2dfa-1.0.2.dist-info/METADATA
ltlf2dfa-1.0.2.dist-info/WHEEL
ltlf2dfa-1.0.2.dist-info/top_level.txt
ltlf2dfa-1.0.2.dist-info/RECORD
