Metadata-Version: 2.1
Name: ltlf2dfa
Version: 1.0.2
Summary: LTLf and PLTLf to Deterministic Finite-state Automata (DFA)
Home-page: https://github.com/whitemech/ltlf2dfa.git
Author: Francesco Fuggitti
Author-email: fuggitti@diag.uniroma1.it
License: GNU Lesser General Public License v3 or later (LGPLv3+)
Keywords: ltlf2dfa
Platform: UNKNOWN
Classifier: Development Status :: 3 - Alpha
Classifier: Intended Audience :: Education
Classifier: License :: OSI Approved :: GNU Lesser General Public License v3 or later (LGPLv3+)
Classifier: Natural Language :: English
Classifier: Programming Language :: Python :: 3
Classifier: Programming Language :: Python :: 3.6
Classifier: Programming Language :: Python :: 3.7
Classifier: Programming Language :: Python :: 3.8
License-File: LICENSE
